{
 "dots": true, 
 "infinite": true,
 "lazyLoad": "ondemand",
 "autoplay": true,
 "autoplaySpeed": 7000,
 "arrows": true,
 "nextArrow":"<img class='a-right control-c next slick-next' src='https://www.loechel-industriebedarf.de/upload/shoppictures_95/tinymce/frontpage_2024/Pfeil_Rechts.png'>",
 "prevArrow":"<img class='a-right control-c next slick-prev' src='https://www.loechel-industriebedarf.de/upload/shoppictures_95/tinymce/frontpage_2024/Pfeil_Links.png'>",
 "responsive": [
				{
                  "breakpoint": 9999,
                  "settings": {
						"slidesToShow":6,
						"slidesToScroll":6
                  }
                },
                {
                  "breakpoint": 1650,
                  "settings": {
						"slidesToShow":5,
						"slidesToScroll":5
                  }
                },
				{
                  "breakpoint": 1400,
                  "settings": {
						"mobileFirst": true,
						"slidesToShow":4,
						"slidesToScroll":4
                  }
                },
				{
                  "breakpoint": 1024,
                  "settings": {
						"mobileFirst": true,
						"slidesToShow":3,
						"slidesToScroll":3
                  }
                },
				{
                  "breakpoint": 768,
                  "settings": {
						"mobileFirst": true,
						"slidesToShow":2,
						"slidesToScroll":2
                  }
                },
				{
                  "breakpoint": 576,
                  "settings": {
						"mobileFirst": true,
						"slidesToShow":1,
						"slidesToScroll":1
                  }
                },
				{
                  "breakpoint": 0,
                  "settings": {
						"mobileFirst": true,
						"slidesToShow":1,
						"slidesToScroll":1
                  }
                }
              ]
}

{
	"grabCursor": false,
	"rewind": true,
	"lazyPreloadPrevNext": 1,
	"pagination": {
		"enabled": false
	},
	"breakpoints": {
		"0": {
			"slidesPerView": 1,
			"slidesPerGroup": 1
		},
		"576": {
			"slidesPerView": 2,
			"slidesPerGroup": 2
		},
		"768": {
			"slidesPerView": 3,
			"slidesPerGroup": 3
		},
		"1024": {
			"slidesPerView": 4,
			"slidesPerGroup": 4
		},
		"1400": {
			"slidesPerView": 5,
			"slidesPerGroup": 5
		},
		"1650": {
			"slidesPerView": 5,
			"slidesPerGroup": 5
		}
	}
}
